{
  "annotations": {
    "list": [
      {
        "builtIn": 1,
        "datasource": {
          "type": "grafana",
          "uid": "-- Grafana --"
        },
        "enable": true,
        "hide": true,
        "iconColor": "rgba(0, 211, 255, 1)",
        "name": "Annotations & Alerts",
        "target": {
          "limit": 100,
          "matchAny": false,
          "tags": [],
          "type": "dashboard"
        },
        "type": "dashboard"
      }
    ]
  },
  "editable": true,
  "fiscalYearStartMonth": 0,
  "graphTooltip": 0,
  "id": 84,
  "links": [],
  "liveNow": false,
  "panels": [
    {
      "datasource": {
        "type": "prometheus",
        "uid": "P4169E866C3094E38"
      },
      "description": "",
      "fieldConfig": {
        "defaults": {
          "color": {
            "mode": "palette-classic"
          },
          "custom": {
            "hideFrom": {
              "legend": false,
              "tooltip": false,
              "viz": false
            }
          },
          "mappings": []
        },
        "overrides": []
      },
      "gridPos": {
        "h": 10,
        "w": 5,
        "x": 0,
        "y": 0
      },
      "id": 2,
      "options": {
        "displayLabels": [
          "percent"
        ],
        "legend": {
          "displayMode": "list",
          "placement": "right",
          "showLegend": true,
          "values": []
        },
        "pieType": "pie",
        "reduceOptions": {
          "calcs": [
            "lastNotNull"
          ],
          "fields": "",
          "values": false
        },
        "tooltip": {
          "mode": "single",
          "sort": "none"
        }
      },
      "pluginVersion": "9.1.7",
      "targets": [
        {
          "datasource": {
            "type": "prometheus",
            "uid": "P4169E866C3094E38"
          },
          "editorMode": "code",
          "expr": "sum by(blobSource) (gitpod_registry_facade_registry_blob_req_dl_total{cluster=~\"$cluster\"})",
          "interval": "",
          "legendFormat": "{{blobSource}}",
          "range": true,
          "refId": "A"
        }
      ],
      "title": "Downloads per source",
      "transparent": true,
      "type": "piechart"
    },
    {
      "datasource": {
        "type": "prometheus",
        "uid": "P4169E866C3094E38"
      },
      "fieldConfig": {
        "defaults": {
          "color": {
            "mode": "palette-classic"
          },
          "custom": {
            "axisCenteredZero": false,
            "axisColorMode": "text",
            "axisGridShow": true,
            "axisLabel": "",
            "axisPlacement": "left",
            "barAlignment": 0,
            "drawStyle": "line",
            "fillOpacity": 0,
            "gradientMode": "none",
            "hideFrom": {
              "legend": false,
              "tooltip": false,
              "viz": false
            },
            "lineInterpolation": "linear",
            "lineWidth": 1,
            "pointSize": 5,
            "scaleDistribution": {
              "type": "linear"
            },
            "showPoints": "auto",
            "spanNulls": false,
            "stacking": {
              "group": "A",
              "mode": "none"
            },
            "thresholdsStyle": {
              "mode": "off"
            }
          },
          "mappings": [],
          "thresholds": {
            "mode": "absolute",
            "steps": [
              {
                "color": "green",
                "value": null
              },
              {
                "color": "red",
                "value": 80
              }
            ]
          },
          "unit": "Bps"
        },
        "overrides": []
      },
      "gridPos": {
        "h": 10,
        "w": 18,
        "x": 5,
        "y": 0
      },
      "id": 3,
      "options": {
        "legend": {
          "calcs": [],
          "displayMode": "list",
          "placement": "bottom",
          "showLegend": true
        },
        "tooltip": {
          "mode": "single",
          "sort": "none"
        }
      },
      "pluginVersion": "9.1.7",
      "targets": [
        {
          "datasource": {
            "type": "prometheus",
            "uid": "P4169E866C3094E38"
          },
          "editorMode": "code",
          "expr": "sum by(blobSource) (rate(gitpod_registry_facade_registry_blob_req_bytes_second_sum{cluster=~\"$cluster\"}[$__rate_interval]))",
          "legendFormat": "__auto",
          "range": true,
          "refId": "A"
        }
      ],
      "title": "Download speed",
      "type": "timeseries"
    },
    {
      "datasource": {
        "type": "prometheus",
        "uid": "P4169E866C3094E38"
      },
      "description": "",
      "fieldConfig": {
        "defaults": {
          "mappings": [],
          "thresholds": {
            "mode": "absolute",
            "steps": [
              {
                "color": "green",
                "value": null
              }
            ]
          },
          "unit": "decbytes"
        },
        "overrides": []
      },
      "gridPos": {
        "h": 10,
        "w": 5,
        "x": 0,
        "y": 10
      },
      "hideTimeOverride": false,
      "id": 6,
      "options": {
        "colorMode": "background",
        "graphMode": "none",
        "justifyMode": "center",
        "orientation": "auto",
        "reduceOptions": {
          "calcs": [
            "last"
          ],
          "fields": "",
          "values": false
        },
        "textMode": "auto"
      },
      "pluginVersion": "9.1.7",
      "targets": [
        {
          "datasource": {
            "type": "prometheus",
            "uid": "P4169E866C3094E38"
          },
          "editorMode": "code",
          "expr": "sum(increase(gitpod_registry_facade_registry_blob_req_bytes_total{cluster=~\"$cluster\"}[24h])) by(blobSource)",
          "interval": "",
          "legendFormat": "{{blobSource}}",
          "range": true,
          "refId": "A"
        }
      ],
      "title": "Download size per source",
      "transparent": true,
      "type": "stat"
    },
    {
      "datasource": {
        "type": "prometheus",
        "uid": "P4169E866C3094E38"
      },
      "fieldConfig": {
        "defaults": {
          "custom": {
            "hideFrom": {
              "legend": false,
              "tooltip": false,
              "viz": false
            },
            "scaleDistribution": {
              "type": "linear"
            }
          }
        },
        "overrides": []
      },
      "gridPos": {
        "h": 10,
        "w": 18,
        "x": 5,
        "y": 10
      },
      "id": 7,
      "options": {
        "calculate": false,
        "cellGap": 1,
        "cellValues": {},
        "color": {
          "exponent": 0.5,
          "fill": "dark-orange",
          "mode": "scheme",
          "reverse": false,
          "scale": "exponential",
          "scheme": "Oranges",
          "steps": 64
        },
        "exemplars": {
          "color": "rgba(255,0,255,0.7)"
        },
        "filterValues": {
          "le": 1e-9
        },
        "legend": {
          "show": true
        },
        "rowsFrame": {
          "layout": "auto"
        },
        "tooltip": {
          "show": false,
          "yHistogram": false
        },
        "yAxis": {
          "axisPlacement": "hidden",
          "reverse": false,
          "unit": "Bps"
        }
      },
      "pluginVersion": "9.1.7",
      "targets": [
        {
          "datasource": {
            "type": "prometheus",
            "uid": "P4169E866C3094E38"
          },
          "editorMode": "code",
          "expr": "sum(\n    rate(gitpod_registry_facade_registry_blob_req_bytes_second_bucket{cluster=~\"$cluster\", blobSource=\"proxy\",le!=\"+Inf\"}[$__rate_interval])\n  ) by (le)\n",
          "legendFormat": "__auto",
          "range": true,
          "refId": "A"
        }
      ],
      "title": "Proxy",
      "type": "heatmap"
    },
    {
      "datasource": {
        "type": "prometheus",
        "uid": "P4169E866C3094E38"
      },
      "fieldConfig": {
        "defaults": {
          "custom": {
            "hideFrom": {
              "legend": false,
              "tooltip": false,
              "viz": false
            },
            "scaleDistribution": {
              "type": "linear"
            }
          }
        },
        "overrides": []
      },
      "gridPos": {
        "h": 10,
        "w": 18,
        "x": 5,
        "y": 20
      },
      "id": 5,
      "options": {
        "calculate": false,
        "cellGap": 1,
        "color": {
          "exponent": 0.5,
          "fill": "dark-orange",
          "mode": "scheme",
          "reverse": false,
          "scale": "exponential",
          "scheme": "Oranges",
          "steps": 64
        },
        "exemplars": {
          "color": "rgba(255,0,255,0.7)"
        },
        "filterValues": {
          "le": 1e-9
        },
        "legend": {
          "show": true
        },
        "rowsFrame": {
          "layout": "auto"
        },
        "tooltip": {
          "show": true,
          "yHistogram": false
        },
        "yAxis": {
          "axisPlacement": "hidden",
          "reverse": false,
          "unit": "Bps"
        }
      },
      "pluginVersion": "9.1.7",
      "targets": [
        {
          "datasource": {
            "type": "prometheus",
            "uid": "P4169E866C3094E38"
          },
          "editorMode": "code",
          "expr": "sum(\n    rate(gitpod_registry_facade_registry_blob_req_bytes_second_bucket{cluster=~\"$cluster\", blobSource=\"blobstore\",le!=\"+Inf\"}[$__rate_interval])\n  ) by (le)\n",
          "legendFormat": "__auto",
          "range": true,
          "refId": "A"
        }
      ],
      "title": "Blobstore",
      "type": "heatmap"
    },
    {
      "datasource": {
        "type": "prometheus",
        "uid": "P4169E866C3094E38"
      },
      "fieldConfig": {
        "defaults": {
          "custom": {
            "hideFrom": {
              "legend": false,
              "tooltip": false,
              "viz": false
            },
            "scaleDistribution": {
              "type": "linear"
            }
          }
        },
        "overrides": []
      },
      "gridPos": {
        "h": 11,
        "w": 18,
        "x": 5,
        "y": 30
      },
      "id": 4,
      "options": {
        "calculate": false,
        "cellGap": 1,
        "color": {
          "exponent": 0.5,
          "fill": "dark-orange",
          "mode": "scheme",
          "reverse": false,
          "scale": "exponential",
          "scheme": "Oranges",
          "steps": 64
        },
        "exemplars": {
          "color": "rgba(255,0,255,0.7)"
        },
        "filterValues": {
          "le": 1e-9
        },
        "legend": {
          "show": true
        },
        "rowsFrame": {
          "layout": "auto"
        },
        "tooltip": {
          "show": true,
          "yHistogram": false
        },
        "yAxis": {
          "axisPlacement": "hidden",
          "reverse": false,
          "unit": "Bps"
        }
      },
      "pluginVersion": "9.1.7",
      "targets": [
        {
          "datasource": {
            "type": "prometheus",
            "uid": "P4169E866C3094E38"
          },
          "editorMode": "code",
          "expr": "sum(\n    rate(gitpod_registry_facade_registry_blob_req_bytes_second_bucket{cluster=~\"$cluster\", blobSource=\"ipfs\",le!=\"+Inf\" }[$__rate_interval])  \n  ) by (le) \n",
          "legendFormat": "__auto",
          "range": true,
          "refId": "A"
        }
      ],
      "title": "IPFS",
      "type": "heatmap"
    }
  ],
  "refresh": "30s",
  "schemaVersion": 37,
  "style": "dark",
  "tags": [],
  "templating": {
    "list": [
      {
        "current": {
          "selected": true,
          "text": [
            "All"
          ],
          "value": [
            "$__all"
          ]
        },
        "datasource": {
          "type": "prometheus",
          "uid": "P4169E866C3094E38"
        },
        "definition": "label_values(up{job=\"registry-facade\"}, cluster)",
        "hide": 0,
        "includeAll": true,
        "multi": true,
        "name": "cluster",
        "options": [],
        "query": {
          "query": "label_values(up{job=\"registry-facade\"}, cluster)",
          "refId": "StandardVariableQuery"
        },
        "refresh": 2,
        "regex": "",
        "skipUrlSync": false,
        "sort": 0,
        "type": "query"
      }
    ]
  },
  "time": {
    "from": "now-24h",
    "to": "now"
  },
  "timepicker": {},
  "timezone": "",
  "title": "Registry facade download bytes",
  "uid": "-5J1T3S4k",
  "version": 2,
  "weekStart": ""
}